keras_microscopy/__init__.py
keras_microscopy/preprocessing/__init__.py
keras_microscopy/preprocessing/image.py
keras_microscopy/preprocessing/iterator.py
keras_microscopy-0.0.1.dist-info/DESCRIPTION.rst
keras_microscopy-0.0.1.dist-info/METADATA
keras_microscopy-0.0.1.dist-info/RECORD
keras_microscopy-0.0.1.dist-info/WHEEL
keras_microscopy-0.0.1.dist-info/metadata.json
keras_microscopy-0.0.1.dist-info/top_level.txt
tests/preprocessing/__init__.py
tests/preprocessing/test_image.py
